hpcflow/__init__.py
hpcflow/_version.py
hpcflow/actions.py
hpcflow/cli.py
hpcflow/command_files.py
hpcflow/commands.py
hpcflow/config.py
hpcflow/core.py
hpcflow/data/__init__.py
hpcflow/data/config.yaml
hpcflow/data/environments_spec_schema.yaml
hpcflow/data/task_schema_spec_schema.yaml
hpcflow/data/workflow_spec_schema.yaml
hpcflow/element.py
hpcflow/environment.py
hpcflow/errors.py
hpcflow/gui.py
hpcflow/hpcflow.py
hpcflow/loop.py
hpcflow/object_list.py
hpcflow/parameters.py
hpcflow/runtime.py
hpcflow/server.py
hpcflow/spec_parse.py
hpcflow/spec_schema.py
hpcflow/task.py
hpcflow/task_schema.py
hpcflow/typing_stubs.py
hpcflow/utils.py
hpcflow/workflow.py
hpcflow_new-0.81.0.dist-info/entry_points.txt
hpcflow_new-0.81.0.dist-info/WHEEL
hpcflow_new-0.81.0.dist-info/METADATA
hpcflow_new-0.81.0.dist-info/RECORD
