Metadata-Version: 2.1
Name: hpcflow-new
Version: 0.81.0
Summary: Computational workflow management
License: MIT
Author: aplowman
Author-email: adam.plowman@manchester.ac.uk
Requires-Python: >=3.7,<3.11
Classifier: License :: OSI Approved :: MIT License
Classifier: Programming Language :: Python :: 3
Classifier: Programming Language :: Python :: 3.10
Classifier: Programming Language :: Python :: 3.7
Classifier: Programming Language :: Python :: 3.8
Classifier: Programming Language :: Python :: 3.9
Provides-Extra: pyinstaller
Requires-Dist: click (>=8.0.4,<9.0.0)
Requires-Dist: pyinstaller (>=4.10,<5.0); extra == "pyinstaller"
Requires-Dist: ruamel.yaml (>=0.17.20,<0.18.0)
Requires-Dist: valida (>=0.2.0,<0.3.0)
Requires-Dist: zarr (>=2.10.3,<3.0.0)
